Metadata-Version: 2.1
Name: odoo14-addon-stock_barcodes
Version: 14.0.4.0.1
Summary: It provides read barcode on stock operations.
Home-page: https://github.com/OCA/stock-logistics-barcode
Author: Tecnativa, Odoo Community Association (OCA)
Author-email: support@odoo-community.org
License: AGPL-3
Classifier: Programming Language :: Python
Classifier: Framework :: Odoo
Classifier: Framework :: Odoo :: 14.0
Classifier: License :: OSI Approved :: GNU Affero General Public License v3
Requires-Python: >=3.6
Requires-Dist: odoo14-addon-web-widget-numeric-step
Requires-Dist: odoo <14.1dev,>=14.0a
